unbabelizer/__init__.py
unbabelizer/__main__.py
unbabelizer/app.py
unbabelizer/cli.py
unbabelizer/config.py
unbabelizer/log.py
unbabelizer/translation.py
unbabelizer/utils.py
unbabelizer/locales/de/LC_MESSAGES/messages.mo
unbabelizer/locales/de/LC_MESSAGES/messages.po
unbabelizer/modals/__init__.py
unbabelizer/modals/confirm_inevitable.py
unbabelizer/modals/po_edit_sc.py
unbabelizer/modals/po_review_sc.py
unbabelizer/modals/po_translation_sc.py
unbabelizer/types/__init__.py
unbabelizer/types/highlighter.py
unbabelizer/types/note.py
unbabelizer/types/subcommand.py
unbabelizer/types/table_row.py
unbabelizer/types/po_file/__init__.py
unbabelizer/types/po_file/handler.py
unbabelizer/types/po_file/tag.py
unbabelizer/types/translation_service/__init__.py
unbabelizer/types/translation_service/config.py
unbabelizer/types/translation_service/service_definition.py
unbabelizer/types/translation_service/service_definitions.py
unbabelizer/types/translation_service/services.py
unbabelizer-1.2.5.dist-info/licenses/LICENSE
unbabelizer-1.2.5.dist-info/licenses/licenses/asciinema.txt
unbabelizer-1.2.5.dist-info/licenses/licenses/babel.txt
unbabelizer-1.2.5.dist-info/licenses/licenses/deep_translator.txt
unbabelizer-1.2.5.dist-info/licenses/licenses/jmespath.txt
unbabelizer-1.2.5.dist-info/licenses/licenses/polib.txt
unbabelizer-1.2.5.dist-info/licenses/licenses/pydantic.txt
unbabelizer-1.2.5.dist-info/licenses/licenses/textual.txt
unbabelizer-1.2.5.dist-info/METADATA
unbabelizer-1.2.5.dist-info/WHEEL
unbabelizer-1.2.5.dist-info/entry_points.txt
unbabelizer-1.2.5.dist-info/top_level.txt
unbabelizer-1.2.5.dist-info/RECORD
