Metadata-Version: 2.4
Name: unbabelizer
Version: 1.2.5
Summary: A CLI tool to translate gettext .po files.
Author-email: Dawid Ciepiela <71898979+sarumaj@users.noreply.github.com>
Keywords: translation,google translate,po files
Classifier: Programming Language :: Python :: 3.12
Classifier: Operating System :: OS Independent
Requires-Python: >=3.12
License-File: LICENSE
License-File: licenses/asciinema.txt
License-File: licenses/babel.txt
License-File: licenses/deep_translator.txt
License-File: licenses/jmespath.txt
License-File: licenses/polib.txt
License-File: licenses/pydantic.txt
License-File: licenses/textual.txt
Requires-Dist: babel==2.17.0
Requires-Dist: deep-translator==1.11.4
Requires-Dist: jmespath==1.0.1
Requires-Dist: polib==1.2.0
Requires-Dist: pydantic==2.12.5
Requires-Dist: textual==6.11.0
Dynamic: license-file
